Metadata-Version: 2.1
Name: openmailer
Version: 0.1.12
Summary: Open-source email automation and delivery engine
Home-page: https://github.com/Devops-Bot-Official/OpenMailer.git
Author: Mohamed Sesay
Author-email: msesay@dee-empire.com
License: MIT
Classifier: Programming Language :: Python :: 3
Classifier: License :: OSI Approved :: MIT License
Classifier: Operating System :: OS Independent
Requires-Python: >=3.7
Requires-Dist: azure-identity
Requires-Dist: azure-keyvault-secrets
Requires-Dist: boto3
Requires-Dist: hvac
Requires-Dist: jinja2
Requires-Dist: python-dotenv
Requires-Dist: pyyaml
Requires-Dist: requests
Requires-Dist: rich
